xboxapi/VERSION
xboxapi/__init__.py
xboxapi/client.py
xboxapi/gamer.py
xboxapi-2.0.1.dist-info/LICENSE
xboxapi-2.0.1.dist-info/METADATA
xboxapi-2.0.1.dist-info/WHEEL
xboxapi-2.0.1.dist-info/top_level.txt
xboxapi-2.0.1.dist-info/RECORD
