Metadata-Version: 2.1
Name: xboxapi
Version: 2.0.1
Summary: XBOX One API
Home-page: https://github.com/mKeRix/xboxapi-python
Author: xapi.us
License: MIT License
Download-URL: https://github.com/mKeRix/xboxapi-python/tarball/2.0.1
Platform: any
Classifier: Programming Language :: Python
Classifier: Development Status :: 3 - Alpha
Classifier: Natural Language :: English
Classifier: Environment :: Web Environment
Classifier: Intended Audience :: Developers
Classifier: License :: OSI Approved :: MIT License
Classifier: Operating System :: OS Independent
Classifier: Topic :: Software Development :: Libraries :: Python Modules
Classifier: Topic :: Games/Entertainment
Requires-Dist: requests
